README.rst
setup.py
simplefsapp_moc/__init__.py
simplefsapp_moc/simplefsapp_moc.py
simplefsapp_moc.egg-info/PKG-INFO
simplefsapp_moc.egg-info/SOURCES.txt
simplefsapp_moc.egg-info/dependency_links.txt
simplefsapp_moc.egg-info/not-zip-safe
simplefsapp_moc.egg-info/requires.txt
simplefsapp_moc.egg-info/top_level.txt