Metadata-Version: 1.0
Name: simplefsapp-moc
Version: 1.0.2
Summary: A demo/testing simplefsapp for the MOC compute environment.
Home-page: http://wiki
Author: FNNDSC
Author-email: dev@babyMRI.org
License: MIT
Platform: UNKNOWN
